grouping/.DS_Store
grouping/Dockerfile
grouping/__init__.py
grouping/cli.py
grouping/config.json
grouping/dbhelper.py
grouping/docker-compose.yml
grouping/requirements.txt
grouping/run_docker.sh
grouping/views.py
grouping/wsgi.py
grouping/.ipynb_checkpoints/Untitled-checkpoint.ipynb
grouping/OutputFolder/.DS_Store
grouping/OutputFolder/CCLF1_RI.csv
grouping/OutputFolder/CCLF8_RI.csv
grouping/OutputFolder/CleanedDataML.csv
grouping/__pycache__/__init__.cpython-36.pyc
grouping/__pycache__/__init__.cpython-38.pyc
grouping/__pycache__/cli.cpython-36.pyc
grouping/__pycache__/cli.cpython-38.pyc
grouping/__pycache__/config.cpython-36.pyc
grouping/__pycache__/config.cpython-38.pyc
grouping/__pycache__/dbhelper.cpython-36.pyc
grouping/__pycache__/dbhelper.cpython-38.pyc
grouping/__pycache__/views.cpython-36.pyc
grouping/__pycache__/views.cpython-38.pyc
grouping/__pycache__/wsgi.cpython-36.pyc
grouping/display/.DS_Store
grouping/display/__init__.py
grouping/static/.DS_Store
grouping/static/css/bootstrap.min.css
grouping/static/css/chosen.css
grouping/static/css/chosen.min.css
grouping/static/css/style.css
grouping/static/display/.DS_Store
grouping/static/js/.DS_Store
grouping/static/js/BsMultiSelect.js
grouping/static/js/chosen.jquery.js
grouping/static/js/chosen.jquery.min.js
grouping/static/js/jquery.dataTables.min.js
grouping/static/js/jquery.table2excel.js
grouping/static/js/sorttable.js
grouping/templates/.DS_Store
grouping/templates/change_val.html
grouping/templates/display.html
grouping/templates/index.html
grouping/templates/index_s3.html
grouping/templates/layout.html
grouping/templates/login.html
grouping/templates/pyspark_code.html
grouping/templates/python_code.html
grouping/templates/save.html
grouping/templates/selection.html
grouping/templates/display/.DS_Store
grouping-0.1.8.dist-info/METADATA
grouping-0.1.8.dist-info/WHEEL
grouping-0.1.8.dist-info/entry_points.txt
grouping-0.1.8.dist-info/top_level.txt
grouping-0.1.8.dist-info/RECORD
