Metadata-Version: 2.1
Name: grouping
Version: 0.1.8
Summary: Display and adjust the grouping results
Home-page: UNKNOWN
Author: Travis Li
Author-email: weixing.li@verisk.com
License: GNU General Public License v3
Platform: any
Requires-Dist: flask
